mns/__init__.py
mns/dataset.py
mns/module.py
mns/model/__init__.py
mns/model/convlstm.py
mns/model/convmlp.py
mns/model/convnalu.py
mns/model/layers.py
mns/model/nalu.py
mns/model/scl.py
machine_number_sense-0.1.0.dist-info/LICENSE
machine_number_sense-0.1.0.dist-info/METADATA
machine_number_sense-0.1.0.dist-info/WHEEL
machine_number_sense-0.1.0.dist-info/top_level.txt
machine_number_sense-0.1.0.dist-info/RECORD
