Metadata-Version: 2.1
Name: machine-number-sense
Version: 0.1.0
Summary: Visual arithmetic reasoning with Machine Number Sense dataset
Home-page: https://github.com/mikomel/machine-number-sense
Author: Mikołaj Małkiński
Author-email: mikolaj.malkinski@gmail.com
License: MIT
Keywords: artificial intelligence,visual arithmetic reasoning,machine number sense
Platform: UNKNOWN
Classifier: Development Status :: 4 - Beta
Classifier: Intended Audience :: Developers
Classifier: License :: OSI Approved :: MIT License
Classifier: Operating System :: OS Independent
Classifier: Programming Language :: Python :: 3.6
Classifier: Topic :: Scientific/Engineering :: Artificial Intelligence
Requires-Python: >=3.6
Requires-Dist: torch (>=1.5)
